alibabacloud_dysmsapi20170525/__init__.py
alibabacloud_dysmsapi20170525/client.py
alibabacloud_dysmsapi20170525/models/__init__.py
alibabacloud_dysmsapi20170525/models/_add_ext_code_sign_request.py
alibabacloud_dysmsapi20170525/models/_add_ext_code_sign_response.py
alibabacloud_dysmsapi20170525/models/_add_ext_code_sign_response_body.py
alibabacloud_dysmsapi20170525/models/_add_short_url_request.py
alibabacloud_dysmsapi20170525/models/_add_short_url_response.py
alibabacloud_dysmsapi20170525/models/_add_short_url_response_body.py
alibabacloud_dysmsapi20170525/models/_add_sms_sign_request.py
alibabacloud_dysmsapi20170525/models/_add_sms_sign_response.py
alibabacloud_dysmsapi20170525/models/_add_sms_sign_response_body.py
alibabacloud_dysmsapi20170525/models/_add_sms_template_request.py
alibabacloud_dysmsapi20170525/models/_add_sms_template_response.py
alibabacloud_dysmsapi20170525/models/_add_sms_template_response_body.py
alibabacloud_dysmsapi20170525/models/_change_signature_qualification_request.py
alibabacloud_dysmsapi20170525/models/_change_signature_qualification_response.py
alibabacloud_dysmsapi20170525/models/_change_signature_qualification_response_body.py
alibabacloud_dysmsapi20170525/models/_check_mobiles_card_support_request.py
alibabacloud_dysmsapi20170525/models/_check_mobiles_card_support_response.py
alibabacloud_dysmsapi20170525/models/_check_mobiles_card_support_response_body.py
alibabacloud_dysmsapi20170525/models/_conversion_data_intl_request.py
alibabacloud_dysmsapi20170525/models/_conversion_data_intl_response.py
alibabacloud_dysmsapi20170525/models/_conversion_data_intl_response_body.py
alibabacloud_dysmsapi20170525/models/_create_card_sms_template_request.py
alibabacloud_dysmsapi20170525/models/_create_card_sms_template_response.py
alibabacloud_dysmsapi20170525/models/_create_card_sms_template_response_body.py
alibabacloud_dysmsapi20170525/models/_create_card_sms_template_shrink_request.py
alibabacloud_dysmsapi20170525-4.4.0.dist-info/LICENSE
alibabacloud_dysmsapi20170525-4.4.0.dist-info/METADATA
alibabacloud_dysmsapi20170525-4.4.0.dist-info/WHEEL
alibabacloud_dysmsapi20170525-4.4.0.dist-info/top_level.txt
alibabacloud_dysmsapi20170525-4.4.0.dist-info/RECORD
